ifi_data/__init__.py
ifi_data/api.py
ifi_data/config.py
ifi_data/exceptions.py
ifi_data/logger.py
ifi_data/metadata.py
ifi_data/restapi.py
ifi_data/cli/__main__.py
ifi_data/creds/init_cred.py
ifi_data/test/__init__.py
ifi_data/test/create.py
ifi_data/test/drop_tables.py
ifi_data/test/grafana.py
ifi_data/test/insert.py
ifi_data/test/live_test.py
ifi_data/test/restapi.py
ifi_data/test/retrieve_data.py
ifi_data/test/single_row.py
ifi_data/test/test_config_api.py
ifi_data/test/config/__init__.py
ifi_data/test/config/allengine.py
ifi_data/test/config/dbconfig.py
ifi_data/test/config/pgengine.py
ifi_data/test/h5/__init__.py
ifi_data/test/h5/test_01_format_detection.py
ifi_data/test/h5/test_02_read_h5.py
ifi_data/test/h5/test_03_ingest_h5_to_db.py
ifi_data/test/h5/test_04_export_h5.py
ifi_data/test/metadata/1.py
ifi_data/test/metadata/2.py
ifi_data/test/metadata/3.py
ifi_data/test/metadata/4.py
ifi_data/test/metadata/__init__.py
ifi_data-0.1.1.dist-info/METADATA
ifi_data-0.1.1.dist-info/WHEEL
ifi_data-0.1.1.dist-info/top_level.txt
ifi_data-0.1.1.dist-info/RECORD
