Metadata-Version: 2.4
Name: ifi_data
Version: 0.1.1
Summary: Gather and organize sensor and time series data with a unified API.
Requires-Python: >=3.12
Requires-Dist: fastapi[standard]>=0.116.1
Requires-Dist: httpx>=0.28.1
Requires-Dist: jupyterlab>=4.4.5
Requires-Dist: pandas==2.3.1
Requires-Dist: platformdirs>=4.3.8
Requires-Dist: polars>=1.29.0
Requires-Dist: psycopg2>=2.9.10
Requires-Dist: pytest>=8.4.0
Requires-Dist: python-dateutil==2.9.0
Requires-Dist: python-dotenv==0.21.0
Requires-Dist: requests>=2.32.3
Requires-Dist: ruff>=0.11.8
Requires-Dist: sqlalchemy==2.0.38
Requires-Dist: tabulate>=0.9.0
Requires-Dist: tomli>=2.2.1
Requires-Dist: tomli-w>=1.2.0
Requires-Dist: uvicorn>=0.34.2
